Metadata-Version: 2.1
Name: pyostal
Version: 0.8
Summary: A Python lightweight Postal API Client
Home-page: http://github.com/rnevarezc/pyostal
Author: Rafael Nevarez
License: MIT
Keywords: postal postalserver email http client events
Platform: UNKNOWN
Classifier: Development Status :: 3 - Alpha
Classifier: Environment :: Web Environment
Classifier: Intended Audience :: Developers
Classifier: Natural Language :: English
Classifier: Operating System :: OS Independent
Classifier: Programming Language :: Python :: 3.9
Classifier: Programming Language :: Python :: 3.10
Classifier: Topic :: Internet :: WWW/HTTP
Classifier: Topic :: Software Development :: Libraries
License-File: LICENSE
